ipython_pygments/__init__.py
ipython_pygments/lexers.py
ipython_pygments-0.1.0.dist-info/LICENSE
ipython_pygments-0.1.0.dist-info/WHEEL
ipython_pygments-0.1.0.dist-info/METADATA
ipython_pygments-0.1.0.dist-info/RECORD
