Metadata-Version: 2.1
Name: ipython-pygments
Version: 0.1.0
Summary: Syntax highlighting for ipython
License: BSD-3-Clause license
Author: Thomas MK
Author-email: tmke@posteo.net
Requires-Python: >=3.6,<4.0
Classifier: License :: Other/Proprietary License
Classifier: Programming Language :: Python :: 3
Classifier: Programming Language :: Python :: 3.10
Classifier: Programming Language :: Python :: 3.6
Classifier: Programming Language :: Python :: 3.7
Classifier: Programming Language :: Python :: 3.8
Classifier: Programming Language :: Python :: 3.9
Requires-Dist: Sphinx (>=4.0)
